Sagittarius/__init__.py
Sagittarius/api_utils.py
Sagittarius/simulate_measurements.py
Sagittarius/simulate_measurements_webserver.py
Sagittarius_api_test-0.13.dist-info/METADATA
Sagittarius_api_test-0.13.dist-info/WHEEL
Sagittarius_api_test-0.13.dist-info/top_level.txt
Sagittarius_api_test-0.13.dist-info/RECORD
