Metadata-Version: 2.1
Name: Sagittarius-api-test
Version: 0.13
Summary: UNKNOWN
Home-page: https://github.com/addiewc/Sagittarius
Author: Sheng Wang Lab
Author-email: mingxz8@uw.edu
License: MIT
Keywords: example project
Platform: UNKNOWN
Classifier: Development Status :: 1 - Planning
Classifier: Intended Audience :: Science/Research
Classifier: License :: OSI Approved :: MIT License
Classifier: Operating System :: POSIX :: Linux
Classifier: Programming Language :: Python :: 3.9
Requires-Dist: torch (==1.9.0)
Requires-Dist: numpy (>=1.21.2)
Requires-Dist: pandas (>=1.3.3)
Requires-Dist: scikit-learn (>=0.24.2)
Requires-Dist: matplotlib (>=3.4.3)
Requires-Dist: seaborn (>=0.11.2)
Requires-Dist: umap-learn (>=0.5.1)
Requires-Dist: anndata (>=0.8.0)
Requires-Dist: statsmodels (>=0.13.0)
Requires-Dist: tqdm (>=4.62.3)
